chatFromDB.py
cuboxGPT.py
db.py
webParser.py
cuboxgpt-0.1.1.dist-info/METADATA
cuboxgpt-0.1.1.dist-info/WHEEL
cuboxgpt-0.1.1.dist-info/entry_points.txt
cuboxgpt-0.1.1.dist-info/top_level.txt
cuboxgpt-0.1.1.dist-info/RECORD
