Metadata-Version: 2.1
Name: cuboxgpt
Version: 0.1.1
Summary: Use GPT to chat/search your large Cubox datasets
Home-page: https://github.com/glazec/cuboxGPT
Author: Glaze
License: MIT
Keywords: Cubox,search,AI,GPT,langchain
Classifier: Development Status :: 3 - Alpha
Classifier: License :: OSI Approved :: MIT License
Classifier: Programming Language :: Python :: 3
Classifier: Programming Language :: Python :: 3.6
Classifier: Programming Language :: Python :: 3.7
Classifier: Programming Language :: Python :: 3.8
Classifier: Programming Language :: Python :: 3.9
Classifier: Programming Language :: Python :: 3.10
Classifier: Programming Language :: Python :: 3.11
Requires-Dist: typer
Requires-Dist: requests
Requires-Dist: bs4
Requires-Dist: rich
Requires-Dist: langchain
Requires-Dist: openai
Requires-Dist: chromadb
Requires-Dist: tiktoken
